textle/__init__.py
textle/__main__.py
textle/config.py
textle/fileref.py
textle/pipeline.py
textle/textlefile.py
textle/cli/__init__.py
textle/cli/autre.py
textle/cli/cli.py
textle/parsers/__init__.py
textle/parsers/pipeline.py
textle/parsers/textlefile.py
textle/steps/__init__.py
textle/steps/pandoc.py
textle/steps/shell_help.py
textle/steps/sinks.py
textle/steps/tex.py
textle-0.1.post1.dist-info/LICENSE
textle-0.1.post1.dist-info/METADATA
textle-0.1.post1.dist-info/WHEEL
textle-0.1.post1.dist-info/entry_points.txt
textle-0.1.post1.dist-info/top_level.txt
textle-0.1.post1.dist-info/RECORD
